odoo8_addon_project_issue_reassign-8.0.1.1.0.99.dev24-py3.8-nspkg.pth
odoo_addons/project_issue_reassign/README.rst
odoo_addons/project_issue_reassign/__init__.py
odoo_addons/project_issue_reassign/__openerp__.py
odoo_addons/project_issue_reassign/project.py
odoo_addons/project_issue_reassign/project_issue_view.xml
odoo_addons/project_issue_reassign/i18n/am.po
odoo_addons/project_issue_reassign/i18n/ar.po
odoo_addons/project_issue_reassign/i18n/bg.po
odoo_addons/project_issue_reassign/i18n/bs.po
odoo_addons/project_issue_reassign/i18n/ca.po
odoo_addons/project_issue_reassign/i18n/ca_ES.po
odoo_addons/project_issue_reassign/i18n/cs.po
odoo_addons/project_issue_reassign/i18n/da.po
odoo_addons/project_issue_reassign/i18n/de.po
odoo_addons/project_issue_reassign/i18n/el.po
odoo_addons/project_issue_reassign/i18n/el_GR.po
odoo_addons/project_issue_reassign/i18n/en_AU.po
odoo_addons/project_issue_reassign/i18n/en_GB.po
odoo_addons/project_issue_reassign/i18n/es.po
odoo_addons/project_issue_reassign/i18n/es_AR.po
odoo_addons/project_issue_reassign/i18n/es_CL.po
odoo_addons/project_issue_reassign/i18n/es_CO.po
odoo_addons/project_issue_reassign/i18n/es_CR.po
odoo_addons/project_issue_reassign/i18n/es_DO.po
odoo_addons/project_issue_reassign/i18n/es_EC.po
odoo_addons/project_issue_reassign/i18n/es_ES.po
odoo_addons/project_issue_reassign/i18n/es_MX.po
odoo_addons/project_issue_reassign/i18n/es_PE.po
odoo_addons/project_issue_reassign/i18n/es_PY.po
odoo_addons/project_issue_reassign/i18n/es_VE.po
odoo_addons/project_issue_reassign/i18n/et.po
odoo_addons/project_issue_reassign/i18n/fa.po
odoo_addons/project_issue_reassign/i18n/fi.po
odoo_addons/project_issue_reassign/i18n/fr.po
odoo_addons/project_issue_reassign/i18n/fr_CA.po
odoo_addons/project_issue_reassign/i18n/fr_CH.po
odoo_addons/project_issue_reassign/i18n/fr_FR.po
odoo_addons/project_issue_reassign/i18n/gl.po
odoo_addons/project_issue_reassign/i18n/gl_ES.po
odoo_addons/project_issue_reassign/i18n/he.po
odoo8_addon_project_issue_reassign-8.0.1.1.0.99.dev24.dist-info/METADATA
odoo8_addon_project_issue_reassign-8.0.1.1.0.99.dev24.dist-info/WHEEL
odoo8_addon_project_issue_reassign-8.0.1.1.0.99.dev24.dist-info/namespace_packages.txt
odoo8_addon_project_issue_reassign-8.0.1.1.0.99.dev24.dist-info/top_level.txt
odoo8_addon_project_issue_reassign-8.0.1.1.0.99.dev24.dist-info/RECORD
